{
  "course": "management",
  "lesson": "management-self",
  "title": "Куда твоё время",
  "description": "Раздели занятия руководителя: высокий leverage — твоё время, или делегировать и убрать",
  "data": {
    "type": "categorize",
    "categories": [
      { "id": "high", "label": "Высокий leverage — твоё время" },
      { "id": "low", "label": "Низкий — делегируй или убери" }
    ],
    "items": [
      { "text": "Разобрать на 1-on-1 план роста сильного сотрудника", "category": "high", "explain": "Рост людей даёт отдачу надолго и его не сделает никто за тебя — это высокий leverage." },
      { "text": "Провести финальное собеседование на ключевую роль", "category": "high", "explain": "Найм — одно из самых высоколеверажных и трудно обратимых действий руководителя." },
      { "text": "Продумать архитектуру нового направления (необратимое решение)", "category": "high", "explain": "Ключевое необратимое решение требует именно твоего времени и не делегируется вслепую." },
      { "text": "Разобрать с командой повторяющийся сбой процесса, чтобы он не повторялся", "category": "high", "explain": "Починка источника проблемы экономит команде десятки часов в будущем — высокий leverage." },
      { "text": "Проговорить с руководителем риски квартала и договориться об апдейтах", "category": "high", "explain": "Managing up влияет на решения наверху и страхует от сюрпризов; это твоя работа, не чужая." },
      { "text": "Дать обратную связь сотруднику, который начал недотягивать, пока рано", "category": "high", "explain": "Ранний разговор дешевле накопленной проблемы — высокая отдача на твоё время." },
      { "text": "Лично проверять каждый рутинный пул-реквест команды", "category": "low", "explain": "Ревью делегируется сильному инженеру: ему рост, тебе разгрузка." },
      { "text": "Вручную собирать еженедельный статус-отчёт из тикетов", "category": "low", "explain": "Рутинная сборка автоматизируется или делегируется — твоего времени она не стоит." },
      { "text": "Пересылать сообщения между двумя командами как «передаст»", "category": "low", "explain": "Посредничество убирают, сводя команды напрямую; иначе ты бутылочное горлышко." },
      { "text": "Сидеть на встрече, где ты не принимаешь решений и тебя не спрашивают", "category": "low", "explain": "Встреча без твоей роли — кандидат на «убрать»: она только дробит день." },
      { "text": "Самому чинить мелкий повторяющийся баг, который закрыл бы дежурный", "category": "low", "explain": "Мелкая повторяющаяся работа делегируется; твой час дороже потратить на leverage." },
      { "text": "Отвечать на один и тот же вопрос в чате лично вместо записи в доку", "category": "low", "explain": "Повторяющийся ответ убирают документацией — один раз записал, дальше не тратишь время." }
    ]
  }
}
